gemini_kit/__init__.py
gemini_kit/core.py
gemini_kit/utils.py
gemini_api_toolkit-0.5.5.dist-info/METADATA
gemini_api_toolkit-0.5.5.dist-info/WHEEL
gemini_api_toolkit-0.5.5.dist-info/licenses/LICENSE
gemini_api_toolkit-0.5.5.dist-info/RECORD
