Metadata-Version: 2.4
Name: gemini-api-toolkit
Version: 0.5.5
Summary: A robust, lightweight Python wrapper for the Google Gemini API.
Project-URL: Homepage, https://github.com/Danielnara24/gemini-api-toolkit
Project-URL: Bug Tracker, https://github.com/Danielnara24/gemini-api-toolkit/issues
Author: Danielnara24
License-File: LICENSE
Classifier: License :: OSI Approved :: MIT License
Classifier: Operating System :: OS Independent
Classifier: Programming Language :: Python :: 3
Requires-Python: >=3.9
Requires-Dist: google-genai
Requires-Dist: numpy
Requires-Dist: pillow
Requires-Dist: pydantic
Requires-Dist: requests
